spinny_bar/__init__.py
spinny_bar/errors.py
spinny_bar/progressBars.py
spinny_bar/spinners.py
spinny_bar-0.1.dist-info/LICENSE
spinny_bar-0.1.dist-info/METADATA
spinny_bar-0.1.dist-info/WHEEL
spinny_bar-0.1.dist-info/top_level.txt
spinny_bar-0.1.dist-info/RECORD
