Metadata-Version: 2.1
Name: spinny_bar
Version: 0.1
License-File: LICENSE
